AUTHORS
ChangeLog
LICENSE
Readme.rst
requirements.txt
setup.cfg
setup.py
tox.ini
regmitter/__init__.py
regmitter/logger.py
regmitter/main.py
regmitter/regmitter.py
regmitter.egg-info/PKG-INFO
regmitter.egg-info/SOURCES.txt
regmitter.egg-info/dependency_links.txt
regmitter.egg-info/entry_points.txt
regmitter.egg-info/not-zip-safe
regmitter.egg-info/pbr.json
regmitter.egg-info/requires.txt
regmitter.egg-info/top_level.txt