Metadata-Version: 1.1
Name: regmitter
Version: 1.0.2
Summary: This utility is designed for transferring docker registries data.
Home-page: https://github.com/FromZeus/regmitter
Author: Daniil Trishkin
Author-email: asteroid566@gmail.com
License: UNKNOWN
Platform: UNKNOWN
Classifier: Intended Audience :: Information Technology
Classifier: Intended Audience :: System Administrators
Classifier: License :: OSI Approved :: Apache Software License
Classifier: Operating System :: POSIX :: Linux
Classifier: Programming Language :: Python
Classifier: Programming Language :: Python :: 2
Classifier: Programming Language :: Python :: 2.7
